{
  "jabatan": {
    "tableName": "jabatan",
    "idField": "jabatan",
    "columns": [
      "nama_jabatan",
      "status_aktif"
    ],
    "displayColumns": [
      "Nama Jabatan",
      "Status"
    ]
  },
  "master_jabatan": {
    "tableName": "master_jabatan",
    "idField": "jabatan_id",
    "columns": [
      "nama_jabatan",
      "environment_id",
      "status_aplikasi_id",
      "status_aktif"
    ],
    "displayColumns": [
      "Nama Jabatan ",
      "Environment",
      "Status Aplikasi",
      "Status"
    ]
  },
  "master3": {
    "tableName": "master3",
    "idField": "coba_id",
    "columns": [
      "nama",
      "status_aktif"
    ],
    "displayColumns": [
      "Nama",
      "Status"
    ]
  }
}